<?xml version="1.0" encoding="UTF-8"?>
<xml>
<li class="toclevel-1 tocsection-1"><a href="#Cyrodiil"><span class="tocnumber">1</span> <span class="toctext">Cyrodiil</span></a></li>
<li class="toclevel-1 tocsection-2"><a href="#Morrowind"><span class="tocnumber">2</span> <span class="toctext">Morrowind</span></a></li>
<li class="toclevel-1 tocsection-3"><a href="#Skyrim"><span class="tocnumber">3</span> <span class="toctext">Skyrim</span></a></li>
<li class="toclevel-1 tocsection-4"><a href="#Black_Marsh"><span class="tocnumber">4</span> <span class="toctext">Black Marsh</span></a></li>
<li class="toclevel-1 tocsection-5"><a href="#Elsweyr"><span class="tocnumber">5</span> <span class="toctext">Elsweyr</span></a></li>
<li class="toclevel-1 tocsection-6"><a href="#Valenwood"><span class="tocnumber">6</span> <span class="toctext">Valenwood</span></a></li>
<li class="toclevel-1 tocsection-7"><a href="#Summerset_Isles"><span class="tocnumber">7</span> <span class="toctext">Summerset Isles</span></a></li>
<li class="toclevel-1 tocsection-8"><a href="#Hammerfell"><span class="tocnumber">8</span> <span class="toctext">Hammerfell</span></a></li>
<li class="toclevel-1 tocsection-9"><a href="#High_Rock"><span class="tocnumber">9</span> <span class="toctext">High Rock</span></a></li>
<li class="toclevel-1 tocsection-10"><a href="#Orsinium"><span class="tocnumber">10</span> <span class="toctext">Orsinium</span></a></li>
<li class="toclevel-1 tocsection-11"><a href="#Sources"><span class="tocnumber">11</span> <span class="toctext">Sources</span></a></li>
</xml>